LICENSE.txt
MANIFEST.in
README.md
requirements.txt
requirements_dev.txt
setup.cfg
setup.py
osc_generator/__init__.py
osc_generator/osc_generator.py
osc_generator/version.py
osc_generator.egg-info/PKG-INFO
osc_generator.egg-info/SOURCES.txt
osc_generator.egg-info/dependency_links.txt
osc_generator.egg-info/entry_points.txt
osc_generator.egg-info/requires.txt
osc_generator.egg-info/top_level.txt
osc_generator/tools/__init__.py
osc_generator/tools/converter.py
osc_generator/tools/coord_calculations.py
osc_generator/tools/man_helpers.py
osc_generator/tools/osi_transformer.py
osc_generator/tools/rulebased.py
osc_generator/tools/scenario_writer.py
osc_generator/tools/utils.py
tests/test_tools/__init__.py
tests/test_tools/test_coord_calculations.py
tests/test_tools/test_man_helpers.py
tests/test_tools/test_osc_generator.py
tests/test_tools/test_rulebased.py
tests/test_tools/test_utils.py