Metadata-Version: 2.1
Name: osc-generator
Version: 0.2.0
Summary: OSC-Generator can be used to generate ASAM OpenSCENARIO files from vehicle data and an ASAM OpenDRIVE file.
Home-page: https://github.com/EFS-OpenSource/OSC-Generator
Author: Axel Aigner et al.
Author-email: axel.aigner@efs-techhub.com
License: UNKNOWN
Project-URL: Bug Tracker, https://github.com/EFS-OpenSource/OSC-Generator/issues
Project-URL: Source Code, https://github.com/EFS-OpenSource/OSC-Generator
Platform: UNKNOWN
Classifier: Development Status :: 3 - Alpha
Classifier: Intended Audience :: Science/Research
Classifier: Intended Audience :: Developers
Classifier: License :: OSI Approved :: Apache Software License
Classifier: Natural Language :: English
Classifier: Programming Language :: Python
Classifier: Programming Language :: Python :: 3
Classifier: Programming Language :: Python :: 3.7
Classifier: Programming Language :: Python :: 3.8
Classifier: Programming Language :: Python :: 3.9
Classifier: Programming Language :: Python :: 3.10
Classifier: Programming Language :: Python :: 3 :: Only
Classifier: Programming Language :: Python :: Implementation :: CPython
Classifier: Topic :: Scientific/Engineering
Classifier: Topic :: Scientific/Engineering :: GIS
Classifier: Topic :: Software Development
Classifier: Typing :: Stubs Only
Classifier: Operating System :: Microsoft :: Windows
Requires-Python: >=3.7
License-File: LICENSE.txt
